{
  "version": "1.0",
  "game": "Elden Ring",
  "schema": "chunked-acts",
  "meta": {
    "author": "Медузка",
    "date": "2026-06-28",
    "description": "Маршрут 100% прохождения для Elden Ring. Акт 7: Запретные земли и Вершины Великанов. Глава 2: Вершины Великанов — полное исследование, данжи, замок Сол, контракты, боссы.",
    "tags": ["elden-ring", "100%", "route", "medusa", "mountaintops"],
    "notes": "Полное исследование Вершин Великанов: карты, данжи (катакомбы, могила героя, пещера призывателя), замок Сол, левая половина Медальона Халигтри, финальный контракт, Огненный Великан, Кузница Великанов."
  },
  "acts": [
    {
      "id": "act7",
      "name": "Запретные земли и Вершины Великанов",
      "order": 7,
      "medusaMood": "joy",
      "medusaState": "glow",
      "summary": "Вершины Великанов — ледяные пустоши, где скрываются последние тайны и величайшие опасности. Здесь мы найдём путь к Огненному Великану и подготовимся к финальной битве.",
      "lore": "Вершины Великанов — это край света, где когда-то обитали древние великаны. Теперь здесь лишь снег, лёд и остатки былой славы. Но именно здесь скрыт ключ к Халигтри — левая половина медальона, которая откроет нам путь к Малении.",
      "chapters": [
        {
          "id": "act7_chapter2",
          "order": 2,
          "actId": "act7",
          "name": "Вершины Великанов",
          "mainGoal": "Полностью исследовать Вершины Великанов, зачистить все данжи, выполнить контракты, получить левую половину Медальона Халигтри, победить Огненного Великана и добраться до Кузницы Великанов.",
          "summary": "От входа в регион до активации Кузницы Великанов — мы пройдём через все ключевые зоны, не упуская ни одного предмета и квеста.",
          "lore": "Вершины Великанов — земля, где заканчивается мир. Здесь, среди вечного снега, обитают древние стражи и чудовища. Мы должны быть сильными и осторожными, чтобы выжить и выполнить нашу миссию.",
          "themeId": "act7_chapter2",
          "background": "act7_chapter2.jpg",
          "medusaState": "glow",
          "medusaMood": "joy",
          "progressWeight": 30,
          "locations": [
            {
              "id": "loc_mountaintops_west_map",
              "chapterId": "act7_chapter2",
              "name": "Карта запада",
              "kind": "стела",
              "summary": "Стела с западной картой Вершин Великанов.",
              "travelType": "пешком",
              "dangerLevel": 2,
              "visibility": "открытая",
              "background": "mountaintops_west_map.jpg",
              "ambientTone": "нейтральный",
              "questIds": ["quest_act7_ch2_01"],
              "connectedQuests": ["quest_act7_ch2_02"],
              "loreShort": "Первая карта.",
              "loreLong": "Карта западной части Вершин Великанов, позволяющая ориентироваться в снежных пустошах.",
              "directionsLoc": "Сойдя с Большого Лифта Ролда, ты сразу увидишь стелу с картой западной части Вершин Великанов. Забери её, а затем следуй по тропе до Руин Замора, где активируй благодать."
            },
            {
              "id": "loc_zamor_ruins",
              "chapterId": "act7_chapter2",
              "name": "Руины Замора",
              "kind": "руины",
              "summary": "Руины, населённые Древними Героями Замора.",
              "travelType": "пешком",
              "dangerLevel": 7,
              "visibility": "открытая",
              "background": "zamor_ruins.jpg",
              "ambientTone": "зловещий",
              "questIds": ["quest_act7_ch2_02", "quest_act7_ch2_03"],
              "connectedQuests": ["quest_act7_ch2_03"],
              "loreShort": "Обитель древних воинов.",
              "loreLong": "Руины Замора — место, где обитают герои древности. Они быстры и опасны, но здесь можно найти ценные предметы.",
              "directionsLoc": "От западной карты следуй по тропе до благодати «Руины Замора». Руины находятся прямо у дороги."
            },
            {
              "id": "loc_giants_mountaintop_catacombs",
              "chapterId": "act7_chapter2",
              "name": "Катакомбы на вершине горы Великанов",
              "kind": "подземелье",
              "summary": "Первое подземелье, содержащее Корень Смерти.",
              "travelType": "пешком",
              "dangerLevel": 7,
              "visibility": "скрытая",
              "background": "giants_mountaintop_catacombs.jpg",
              "ambientTone": "зловещий",
              "questIds": ["quest_act7_ch2_04"],
              "connectedQuests": ["quest_act7_ch2_05"],
              "loreShort": "Усыпальница с тайнами.",
              "loreLong": "Эти катакомбы скрывают Корень Смерти. Внутри — лабиринт с падающими лезвиями и боссом-стражем.",
              "directionsLoc": "Расположены сразу за Руинами Замора, перед первым Большим Цепным Мостом. При входе появится сообщение «Звериное око трепещет»."
            },
            {
              "id": "loc_guardians_garrison",
              "chapterId": "act7_chapter2",
              "name": "Гарнизон Стражей",
              "kind": "форт",
              "summary": "Небольшой форт за первым Цепным Мостом.",
              "travelType": "пешком",
              "dangerLevel": 6,
              "visibility": "открытая",
              "background": "guardians_garrison.jpg",
              "ambientTone": "нейтральный",
              "questIds": ["quest_act7_ch2_05"],
              "connectedQuests": ["quest_act7_ch2_06"],
              "loreShort": "Оплот огненных монахов.",
              "loreLong": "Гарнизон Стражей охраняет второй мост. Здесь можно найти ресурсы и расходники.",
              "directionsLoc": "Перейди первый Цепной Мост, затем Гарнизон Стражей находится на восточной стороне, перед вторым мостом."
            },
            {
              "id": "loc_east_mountaintops_map",
              "chapterId": "act7_chapter2",
              "name": "Карта востока",
              "kind": "стела",
              "summary": "Стела с восточной картой Вершин Великанов.",
              "travelType": "пешком",
              "dangerLevel": 4,
              "visibility": "открытая",
              "background": "east_mountaintops_map.jpg",
              "ambientTone": "нейтральный",
              "questIds": ["quest_act7_ch2_06"],
              "connectedQuests": ["quest_act7_ch2_07"],
              "loreShort": "Вторая карта.",
              "loreLong": "Восточная карта открывает путь к Замку Сол и другим важным локациям.",
              "directionsLoc": "После второго Цепного Моста, на пути к вершине, найди стелу с восточной картой."
            },
            {
              "id": "loc_giant_conquering_hero_grave",
              "chapterId": "act7_chapter2",
              "name": "Могила героя-победителя великанов",
              "kind": "подземелье",
              "summary": "Сложное подземелье с огненными ловушками и стражами.",
              "travelType": "пешком",
              "dangerLevel": 8,
              "visibility": "скрытая",
              "background": "giant_conquering_hero_grave.jpg",
              "ambientTone": "зловещий",
              "questIds": ["quest_act7_ch2_07"],
              "connectedQuests": ["quest_act7_ch2_08"],
              "loreShort": "Гробница победителя.",
              "loreLong": "Эта могила полна ловушек и стражей. Здесь можно найти уникальное оружие и заклинания.",
              "directionsLoc": "Находится к западу от Катакомб на вершине горы Великанов, но добраться до неё непросто — нужно скакать на запад/юго-запад от благодати «Могильный столб великанов» (Giants' Gravepost) и совершить прыжок."
            },
            {
              "id": "loc_castle_sol",
              "chapterId": "act7_chapter2",
              "name": "Замок Сол",
              "kind": "замок",
              "summary": "Ключевая локация, где можно найти левую половину Медальона Халигтри.",
              "travelType": "пешком",
              "dangerLevel": 8,
              "visibility": "открытая",
              "background": "castle_sol.jpg",
              "ambientTone": "зловещий",
              "questIds": ["quest_act7_ch2_08", "quest_act7_ch2_09"],
              "connectedQuests": ["quest_act7_ch2_09"],
              "loreShort": "Цитадель снега.",
              "loreLong": "Замок Сол — крепость на востоке Вершин Великанов. Здесь обитают Изгнанные Рыцари, а на вершине нас ждёт Командир Ниалл, охраняющий левую половину Медальона Халигтри.",
              "directionsLoc": "Замок Сол находится на северо-востоке Вершин Великанов. От благодати «Древние заснеженные руины долины» двигайся на север, пересеки мост и спустись на нижний склон."
            },
            {
              "id": "loc_spiritcallers_cave",
              "chapterId": "act7_chapter2",
              "name": "Пещера Призывателя Духов",
              "kind": "пещера",
              "summary": "Пещера с Улитками-Призывателями и дуэтом Кожистых.",
              "travelType": "пешком",
              "dangerLevel": 8,
              "visibility": "скрытая",
              "background": "spiritcallers_cave.jpg",
              "ambientTone": "зловещий",
              "questIds": ["quest_act7_ch2_10"],
              "connectedQuests": ["quest_act7_ch2_11"],
              "loreShort": "Логово призывателей.",
              "loreLong": "Здесь обитают улитки, призывающие духов. В конце — дуэт Кожистых, дающий мощный талисман.",
              "directionsLoc": "На северо-востоке Вершин Великанов, к северо-востоку от Гарнизона Стражей. Для входа требуется 2 Мечевидных ключа."
            },
            {
              "id": "loc_juno_hoslow_spot",
              "chapterId": "act7_chapter2",
              "name": "Хижина Возвышенного",
              "kind": "хижина",
              "summary": "Место финального контракта Вулканова поместья.",
              "travelType": "пешком",
              "dangerLevel": 7,
              "visibility": "открытая",
              "background": "juno_hoslow_spot.jpg",
              "ambientTone": "нейтральный",
              "questIds": ["quest_act7_ch2_11"],
              "connectedQuests": ["quest_act7_ch2_12"],
              "loreShort": "Последняя охота.",
              "loreLong": "У этой хижины находится красный знак призыва Юно Хослоу — финальный контракт Вулканова поместья.",
              "directionsLoc": "На востоке Вершин Великанов, у «Хижины Возвышенного» (Shack of the Lofty), появляется красный знак призыва."
            },
            {
              "id": "loc_fire_giant_arena",
              "chapterId": "act7_chapter2",
              "name": "Арена Огненного Великана",
              "kind": "арена",
              "summary": "Место битвы с Огненным Великаном.",
              "travelType": "пешком",
              "dangerLevel": 9,
              "visibility": "открытая",
              "background": "fire_giant_arena.jpg",
              "ambientTone": "зловещий",
              "questIds": ["quest_act7_ch2_12"],
              "connectedQuests": ["quest_act7_ch2_13"],
              "loreShort": "Поле битвы с титаном.",
              "loreLong": "Здесь, на заснеженной равнине, нас ждёт Огненный Великан — последний из своего рода. Победа над ним откроет путь к Кузнице.",
              "directionsLoc": "После зачистки опциональных зон двигайся на восток к огромной арене Огненного Великана."
            },
            {
              "id": "loc_forge_of_the_giants",
              "chapterId": "act7_chapter2",
              "name": "Кузница Великанов",
              "kind": "кузница",
              "summary": "Конечная точка региона, где можно сжечь Древо Эрд.",
              "travelType": "пешком",
              "dangerLevel": 2,
              "visibility": "открытая",
              "background": "forge_of_the_giants.jpg",
              "ambientTone": "таинственный",
              "questIds": ["quest_act7_ch2_13"],
              "connectedQuests": [],
              "loreShort": "Последнее святилище.",
              "loreLong": "Здесь, у Кузницы, мы можем сжечь Древо Эрд. Это необратимый шаг, поэтому мы должны быть уверены, что все дела завершены.",
              "directionsLoc": "После победы над Огненным Великаном двигайся на северо-восток к Кузнице Великанов. Поднимись по цепи и активируй благодать «Кузница Великанов»."
            }
          ],
          "quests": [
            {
              "id": "quest_act7_ch2_01",
              "order": 1,
              "chapterId": "act7_chapter2",
              "locationId": "loc_mountaintops_west_map",
              "type": "main",
              "priority": 9,
              "importance": 70,
              "importanceLabel": "средняя",
              "title": "Карта запада и благодать Руин Замора",
              "summary": "Забрать карту запада и активировать благодать.",
              "directions": "Сойди с Большого Лифта Ролда и сразу забери карту у стелы. Затем следуй по тропе до Руин Замора и активируй благодать.",
              "goal": "Погасший, мы в Вершинах Великанов! Вокруг белым-бело, и ветер поёт ледяные песни. Сразу за лифтом стоит стела — возьми там первую карту, чтобы не заблудиться в этом снежном безмолвии. А потом скачи по тропе вперёд, к Руинам Замора, где нас ждёт огонь благодати и неожиданная встреча.",
              "context": "Начало исследования региона.",
              "requires": [],
              "unlocks": ["quest_act7_ch2_02"],
              "expanded": true,
              "xp": 30,
              "xpRule": "fixed",
              "xpReason": "Вход в регион.",
              "progressPercentInChapter": 3,
              "progressWeight": 1,
              "medusa": {
                "stateOnStart": "glow",
                "stateOnComplete": "delight",
                "commentOnStart": "Ух, какой холод! Но смотри, вон там у стелы лежит карта. А дальше, в руинах, горит благодать, и мне кажется, нас там кто-то ждёт… знакомый и тревожный.",
                "commentOnComplete": "Благодать горит, словно тёплый уголёк в этой ледяной пустыне. Мы готовы к приключениям!",
                "thoughts": "Вершины Великанов... Здесь даже воздух звенит от древней магии. Мы ступаем по костям титанов."
              },
              "lore": "Карта западных Вершин открывает путь к руинам и первым подземельям. Говорят, здесь когда-то охотились на великанов.",
              "rewards": ["Карта: Вершины великанов, запад", "Благодать «Руины Замора»"],
              "stateEffects": ["Открыта западная карта"]
            },
            {
              "id": "quest_act7_ch2_02",
              "order": 2,
              "chapterId": "act7_chapter2",
              "locationId": "loc_zamor_ruins",
              "type": "side",
              "priority": 8,
              "importance": 75,
              "importanceLabel": "средняя",
              "title": "Встреча с Шабрири",
              "summary": "Поговорить или убить Шабрири у благодати.",
              "directions": "У благодати в Руинах Замора ты встретишь Шабрири. Поговори с ним (или убей). Забери сет Ронина.",
              "goal": "У костра Руин Замора нас ждёт... Юра? Нет, это Шабрири, занявший его тело. Его глаза горят жёлтым пламенем, и он будет говорить о спасении Мелины через Яростное Пламя. Выслушай его, если хочешь, или убей — сет Ронина в любом случае станет нашим.",
              "context": "Шабрири — важный NPC для концовки «Владыка Яростного Пламени».",
              "requires": ["quest_act7_ch2_01"],
              "unlocks": ["quest_act7_ch2_03"],
              "expanded": true,
              "xp": 30,
              "xpRule": "fixed",
              "xpReason": "Взаимодействие с ключевым NPC.",
              "progressPercentInChapter": 3,
              "progressWeight": 1,
              "medusa": {
                "stateOnStart": "glow",
                "stateOnComplete": "calm",
                "commentOnStart": "Шабрири говорит сладко, но от его слов у меня мурашки по... по моему прозрачному телу. Он хочет, чтобы мы сожгли всё, даже себя. Решать тебе, но мы хотя бы возьмём его плащ.",
                "commentOnComplete": "Мы поговорили с безумцем в теле друга и забрали сет Ронина. Теперь мы знаем, что у Мелины есть другой путь, хоть и страшный.",
                "thoughts": "Шабрири — как испорченное зеркало. Он показывает правду о Яростном Пламени, и она ужасает."
              },
              "lore": "Шабрири — слуга Трёх Пальцев, одержимый идеей сжечь всё сущее. Он манипулирует даже смертью, вселяясь в тела, чтобы вести избранных к хаосу.",
              "rewards": ["Сет Ронина"],
              "stateEffects": ["Квест Шабрири активирован"]
            },
            {
              "id": "quest_act7_ch2_03",
              "order": 3,
              "chapterId": "act7_chapter2",
              "locationId": "loc_zamor_ruins",
              "type": "side",
              "priority": 8,
              "importance": 75,
              "importanceLabel": "средняя",
              "title": "Кузнечная колокольная сфера рудокопа 3",
              "summary": "Забрать колокольную сферу и заклинание в руинах.",
              "directions": "Обыщи Руины Замора, найди Кузнечную колокольную сферу рудокопа 3, заклинание «Ледяная буря Замора» и убей скарабея с Тусклым Кузнечным Камнем [7].",
              "goal": "Эти руины полны сокровищ! Нам нужно найти здесь Кузнечную колокольную сферу рудокопа 3 — она позволит покупать камни [5] и [6] у торговцев в Круглом столе! А ещё тут можно найти ледяное заклинание и убить скарабея с редким камнем.",
              "context": "Колокольная сфера критически важна для улучшения оружия в поздней игре.",
              "requires": ["quest_act7_ch2_02"],
              "unlocks": ["quest_act7_ch2_04"],
              "expanded": true,
              "xp": 40,
              "xpRule": "scaled",
              "xpReason": "Сбор ключевых предметов.",
              "progressPercentInChapter": 4,
              "progressWeight": 2,
              "medusa": {
                "stateOnStart": "glow",
                "stateOnComplete": "delight",
                "commentOnStart": "Ищи сферу! Она звякнет, как колокольчик, и наши клинки больше никогда не затупятся. И не забудь того жука-скарабея, он прячет камень.",
                "commentOnComplete": "Мы собрали всё до последней крошки! Теперь мы можем купить целую гору кузнечных камней и заточить всё, что душе угодно.",
                "thoughts": "Колокольная сфера — это свобода. Свобода делать оружие таким же острым, как наши чувства."
              },
              "lore": "Кузнечная колокольная сфера рудокопа 3 — это ключ к бесконечным кузнечным камням [5] и [6], которые так нужны, чтобы подготовиться к финалу.",
              "rewards": ["Кузнечная колокольная сфера рудокопа 3", "Заклинание «Ледяная буря Замора»", "Тусклый Кузнечный Камень [7]"],
              "stateEffects": ["Получена колокольная сфера", "Получено заклинание"]
            },
            {
              "id": "quest_act7_ch2_04",
              "order": 4,
              "chapterId": "act7_chapter2",
              "locationId": "loc_giants_mountaintop_catacombs",
              "type": "boss",
              "priority": 8,
              "importance": 75,
              "importanceLabel": "средняя",
              "title": "Катакомбы на вершине горы Великанов",
              "summary": "Пройти катакомбы, найти скрытый рычаг и победить Стража Погребения, получить Корень Смерти.",
              "directions": "Найди катакомбы перед первым Цепным Мостом. Пройди подземелье, найди скрытый рычаг над статуей на верхнем уровне, затем пройди через комнату с падающими лезвиями и победи Стража Погребения.",
              "goal": "Спустимся в катакомбы, полные жутких импов и ловушек. Тут есть скрытый рычаг над статуей — он откроет путь через комнату с падающими лезвиями. В конце нас ждёт Страж Погребения. Победим его и заберём Корень Смерти для нашего старого звериного друга Гуранка!",
              "context": "Корень Смерти нужен для квеста Гуранка.",
              "requires": ["quest_act7_ch2_03"],
              "unlocks": ["quest_act7_ch2_05"],
              "expanded": true,
              "xp": 60,
              "xpRule": "scaled",
              "xpReason": "Зачистка подземелья и получение Корня Смерти.",
              "progressPercentInChapter": 6,
              "progressWeight": 2,
              "medusa": {
                "stateOnStart": "afraid",
                "stateOnComplete": "delight",
                "commentOnStart": "Здесь темно и пахнет старой кровью. Не пропусти рычаг наверху, он спрятан за статуей! Гуранк будет рад получить эту кость.",
                "commentOnComplete": "Катакомбы зачищены! Ещё один Корень Смерти в нашу коллекцию. Гуранк, наверное, уже чувствует его запах.",
                "thoughts": "Корни Смерти — это осколки проклятия. Гуранк пожирает их, чтобы сдержать тьму."
              },
              "lore": "Катакомбы скрывают Корень Смерти — фрагмент той силы, что убила Годвина. Гуранк, зверь-клирик, жаждет их, чтобы питать свою силу.",
              "rewards": ["Корень Смерти"],
              "stateEffects": ["Получен Корень Смерти"]
            },
            {
              "id": "quest_act7_ch2_05",
              "order": 5,
              "chapterId": "act7_chapter2",
              "locationId": "loc_guardians_garrison",
              "type": "main",
              "priority": 8,
              "importance": 70,
              "importanceLabel": "средняя",
              "title": "Пересечение мостов и восточная карта",
              "summary": "Пересечь два цепных моста, пройти гарнизон и забрать восточную карту.",
              "directions": "Перейди первый Цепной Мост, пройди через Гарнизон Стражей, затем перейди второй Цепной Мост и найди стелу с восточной картой.",
              "goal": "Впереди два огромных цепных моста! Пройдём через Гарнизон Стражей, где огненные монахи до сих пор жгут свои костры, соберём всё полезное и доберёмся до восточной стелы с картой. Она откроет нам путь к замку Сол и вулканам.",
              "context": "Открытие восточной части региона.",
              "requires": ["quest_act7_ch2_04"],
              "unlocks": ["quest_act7_ch2_06"],
              "expanded": true,
              "xp": 35,
              "xpRule": "fixed",
              "xpReason": "Продвижение по региону.",
              "progressPercentInChapter": 4,
              "progressWeight": 1,
              "medusa": {
                "stateOnStart": "glow",
                "stateOnComplete": "delight",
                "commentOnStart": "Эти мосты висят над пропастью, как струны. А за ними — восток, где снег становится огнём. Давай возьмём карту, чтобы знать дорогу!",
                "commentOnComplete": "Мы на востоке! Карта показывает замок и много интересного. Вперёд, к новым загадкам!",
                "thoughts": "Цепные мосты — это как ниточки, связывающие разные судьбы. За каждым поворотом ждёт новое испытание."
              },
              "lore": "Цепные мосты соединяют западную и восточную части Вершин Великанов, которые когда-то враждовали. Восточная карта ведёт к замку Сол, где хранится великая тайна.",
              "rewards": ["Карта: Вершины великанов, восток"],
              "stateEffects": ["Открыта восточная карта"]
            },
            {
              "id": "quest_act7_ch2_06",
              "order": 6,
              "chapterId": "act7_chapter2",
              "locationId": "loc_giant_conquering_hero_grave",
              "type": "boss",
              "priority": 8,
              "importance": 75,
              "importanceLabel": "средняя",
              "title": "Могила героя-победителя великанов",
              "summary": "Пройти сложное подземелье, используя Мечевидные ключи, и получить уникальное оружие.",
              "directions": "Найди могилу и войди. Используй два Мечевидных ключа для доступа к ценным комнатам. Пройди через ловушки и победи стражей. В конце получи Канделябр Черепной Сосуд.",
              "goal": "В этой могиле покоятся герои, что убивали великанов. Тут полно ловушек и иллюзорных стен. Нам понадобятся два Мечевидных ключа, чтобы открыть все секреты и добыть легендарный Канделябр Черепной Сосуд — оружие, которое само поёт песни войны!",
              "context": "Опциональный данж с уникальным оружием.",
              "requires": ["quest_act7_ch2_05"],
              "unlocks": ["quest_act7_ch2_07"],
              "expanded": true,
              "xp": 60,
              "xpRule": "scaled",
              "xpReason": "Зачистка сложного подземелья.",
              "progressPercentInChapter": 6,
              "progressWeight": 2,
              "medusa": {
                "stateOnStart": "afraid",
                "stateOnComplete": "delight",
                "commentOnStart": "Ловушки! Огонь! Но я знаю, что в конце нас ждёт оружие, достойное легенд. Ищи иллюзорные стены и не экономь ключи.",
                "commentOnComplete": "Могила героя пройдена! Канделябр сияет у нас в руках. Мы достойны памяти тех, кто победил титанов.",
                "thoughts": "Герои, что лежат здесь, сражались с великанами. Их оружие — это не просто сталь, это продолжение их воли."
              },
              "lore": "Могила героя-победителя великанов хранит Канделябр Черепной Сосуд — оружие, выкованное из костей тех, кто сражался на этой земле.",
              "rewards": ["Заклинание «Пламя, защити меня»", "Канделябр Черепной Сосуд", "Могильные Цветы (7, 8, 9)"],
              "stateEffects": ["Могила героя пройдена"]
            },
            {
              "id": "quest_act7_ch2_07",
              "order": 7,
              "chapterId": "act7_chapter2",
              "locationId": "loc_castle_sol",
              "type": "boss",
              "priority": 10,
              "importance": 100,
              "importanceLabel": "высокая",
              "title": "Замок Сол — левая половина Медальона Халигтри",
              "summary": "Зачистить замок, победить Командира Ниалла и забрать левую половину Медальона Халигтри.",
              "directions": "Зайди в Замок Сол, пройди через Изгнанных Рыцарей, поднимись на вершину и сразись с Командиром Ниаллом. Победи его, затем забери медальон у края обрыва за ареной.",
              "goal": "Вот он, Замок Сол, где правит вечная зима. На его вершине Командир Ниалл, старый воин с протезом, и его призрачные рыцари. Сначала убей двух мечников, которых он призовёт, а потом срази его самого! После боя поднимись к обрыву и забери левую половину Тайного медальона Халигтри — без него мы не попадём к Малении!",
              "context": "Этот предмет ОБЯЗАТЕЛЕН для доступа к Халигтри и Малении.",
              "requires": ["quest_act7_ch2_06"],
              "unlocks": ["quest_act7_ch2_08"],
              "expanded": true,
              "xp": 80,
              "xpRule": "scaled",
              "xpReason": "Победа над боссом и получение ключевого предмета.",
              "progressPercentInChapter": 8,
              "progressWeight": 3,
              "medusa": {
                "stateOnStart": "afraid",
                "stateOnComplete": "delight",
                "commentOnStart": "Ниалл стоит, как замёрзший великан! Его рыцари — духи, но их мечи реальны. Помни: сначала призраки, потом командир. А за ним — медальон, ключ к Халигтри!",
                "commentOnComplete": "Ниалл пал, и левая половина медальона у нас! Теперь осталось соединить её с правой, и путь к Священному Древу будет открыт!",
                "thoughts": "Этот медальон — как билет в иной мир. Маления ждёт, и мы идём к ней."
              },
              "lore": "Левая половина Медальона Халигтри хранилась в Замке Сол как величайшая реликвия. Она откроет нам путь в Освящённое Снежное Поле, а оттуда — к самому Священному Древу.",
              "rewards": ["Тайный медальон Халигтри (левая половина)", "Протез Ветерана"],
              "stateEffects": ["Получена левая половина Медальона Халигтри"]
            },
            {
              "id": "quest_act7_ch2_08",
              "order": 8,
              "chapterId": "act7_chapter2",
              "locationId": "loc_spiritcallers_cave",
              "type": "boss",
              "priority": 9,
              "importance": 85,
              "importanceLabel": "высокая",
              "title": "Пещера Призывателя Духов",
              "summary": "Пройти пещеру, убить Улиток-Призывателей и победить дуэт Кожистых.",
              "directions": "Найди пещеру (требуется 2 Мечевидных ключа). Внутри убей улиток-призывателей, затем сразись с дуэтом Кожистых (Апостол и Благородный) и получи талисман.",
              "goal": "Чтобы войти в эту пещеру, нужно два Мечевидных ключа. Внутри хитрые улитки призывают призраков. Убей сначала их, чтобы духи исчезли! А в конце нас ждёт дуэт Кожистых — Апостол и Благородный. Победим их и получим талисман, который будет лечить нас в бою!",
              "context": "Талисман «Пелена Божественной Кожи» восстанавливает здоровье при серии ударов.",
              "requires": ["quest_act7_ch2_07"],
              "unlocks": ["quest_act7_ch2_09"],
              "expanded": true,
              "xp": 70,
              "xpRule": "scaled",
              "xpReason": "Победа над дуэтом и получение талисмана.",
              "progressPercentInChapter": 7,
              "progressWeight": 2,
              "medusa": {
                "stateOnStart": "afraid",
                "stateOnComplete": "delight",
                "commentOnStart": "Улитки! Кто бы мог подумать, что они такие опасные? Сначала убиваем их, а потом — двух толстяков в коже. Но талисман того стоит!",
                "commentOnComplete": "Мы порвали их кожу! Теперь «Пелена Божественной Кожи» наша. Каждый удар будет возвращать нам жизненную силу.",
                "thoughts": "Кожа — это жуткая сила, но мы обратим её во благо. Этот талисман спасёт нас не раз."
              },
              "lore": "Пещера Призывателя Духов — это питомник для улиток, которых использовали Божественные Кожистые для своих ритуалов. Талисман, что мы нашли, пропитан их древней магией самовосстановления.",
              "rewards": ["Пелена Божественной Кожи", "Ритуал Чёрного Пламени", "Сет Белого Тростника", "70,000 рун"],
              "stateEffects": ["Пещера зачищена", "Получен талисман"]
            },
            {
              "id": "quest_act7_ch2_09",
              "order": 9,
              "chapterId": "act7_chapter2",
              "locationId": "loc_juno_hoslow_spot",
              "type": "boss",
              "priority": 9,
              "importance": 85,
              "importanceLabel": "высокая",
              "title": "Финальный контракт — Юно Хослоу",
              "summary": "Выполнить финальный контракт Вулканова поместья.",
              "directions": "Найди красный знак призыва у Хижины Возвышенного. Активируй его и победи Юно Хослоу. Вернись к Танит (или награда придёт позже) за «Пришедшую Камею».",
              "goal": "У Хижины Возвышенного горит красный знак. Это Юно Хослоу, брат Диаллоса и последняя цель Вулканова поместья. Он быстр и ранит кровотечением, но мы обязаны победить его, чтобы завершить все контракты Танит и получить «Пришедшую Камею». Это нужно сделать ДО того, как мы сожжём Древо!",
              "context": "Этот контракт доступен только после выполнения всех предыдущих контрактов Танит. Если не выполнить до сожжения Древа, станет недоступен.",
              "requires": ["quest_act7_ch2_08", "quest_act5_ch3_07"],
              "unlocks": ["quest_act7_ch2_10"],
              "expanded": true,
              "xp": 60,
              "xpRule": "scaled",
              "xpReason": "Выполнение финального контракта.",
              "progressPercentInChapter": 6,
              "progressWeight": 2,
              "medusa": {
                "stateOnStart": "afraid",
                "stateOnComplete": "delight",
                "commentOnStart": "Это последний контракт! Хослоу — рыцарь крови, и его хлыст разрывает плоть. Но мы не можем отступить — Танит ждёт.",
                "commentOnComplete": "Юно мёртв. Мы принесли Танит последнюю голову. Теперь мы — лучшие охотники Вулканова поместья!",
                "thoughts": "Хослоу был благородным, но его выбор привёл его сюда. Эта смерть — печальный финал рода."
              },
              "lore": "Юно Хослоу — старший брат Диаллоса, павший рыцарь. Его контракт был последним испытанием для нас от Танит, и мы его прошли.",
              "rewards": ["Пришедшая Камея"],
              "stateEffects": ["Финальный контракт выполнен"]
            },
            {
              "id": "quest_act7_ch2_10",
              "order": 10,
              "chapterId": "act7_chapter2",
              "locationId": "loc_fire_giant_arena",
              "type": "boss",
              "priority": 10,
              "importance": 100,
              "importanceLabel": "высокая",
              "title": "Огненный Великан",
              "summary": "Победить Огненного Великана и получить его Великую Руну и Память.",
              "directions": "Дойди до арены Огненного Великана. Используй Торрента для манёвров. В первой фазе атакуй его левую ногу. Во второй фазе держись у спины и бей по рукам и ногам. Призови Александра, если он доступен.",
              "goal": "Вот он, Погасший — последний Огненный Великан! Его левая нога перевязана, это его слабое место в первой фазе. Бей туда, уклоняйся от кастрюли с огнём и призови Александра, если он здесь! Во второй фазе великан откроет глаз на груди и станет изрыгать пламя — держись у спины. Торрент поможет догнать его. Победим, и путь к Кузнице будет наш!",
              "context": "Обязательный босс для продолжения сюжета.",
              "requires": ["quest_act7_ch2_09"],
              "unlocks": ["quest_act7_ch2_11"],
              "expanded": true,
              "xp": 120,
              "xpRule": "scaled",
              "xpReason": "Победа над главным боссом региона.",
              "progressPercentInChapter": 10,
              "progressWeight": 4,
              "medusa": {
                "stateOnStart": "afraid",
                "stateOnComplete": "delight",
                "commentOnStart": "Он огромный, как гора! Левая нога хрустит — целься туда! А когда он ляжет на землю и откроет глаз, берегись огня из живота. Александр, друг, помоги нам!",
                "commentOnComplete": "Великан пал! Последний из титанов повержен нами. Память о нём и его руна — теперь наши трофеи.",
                "thoughts": "Огненный Великан был хранителем пламени, которое мы идём зажигать. Его смерть — это великая жертва."
              },
              "lore": "Огненный Великан — последний из расы, что владела Кузницей. Он был проклят стеречь пламя, и теперь мы его освободили.",
              "rewards": ["Великая Руна Огненного Великана", "Память Огненного Великана"],
              "stateEffects": ["Огненный Великан побеждён"]
            },
            {
              "id": "quest_act7_ch2_11",
              "order": 11,
              "chapterId": "act7_chapter2",
              "locationId": "loc_forge_of_the_giants",
              "type": "main",
              "priority": 9,
              "importance": 85,
              "importanceLabel": "высокая",
              "title": "Кузница Великанов — точка невозврата",
              "summary": "Добраться до Кузницы, активировать благодать, принять решение о сожжении Древа.",
              "directions": "После победы над Великаном двигайся на северо-восток к Кузнице. Поднимись по цепи и активируй благодать. Убедись, что все квесты закрыты, затем прими решение о сожжении Древа.",
              "goal": "Мы у Кузницы Великанов! Здесь, на краю чаши, ждёт благодать. Но помни, Погасший: это точка невозврата. Если мы пойдём дальше и позволим Мелине сжечь Древо (или сделаем это сами), весь мир изменится, и многие наши друзья уйдут. Проверь все квесты, заверши дела... а потом сделаем этот шаг вместе.",
              "context": "Это необратимый шаг. После него многие NPC исчезнут.",
              "requires": ["quest_act7_ch2_10"],
              "unlocks": [],
              "expanded": true,
              "xp": 40,
              "xpRule": "fixed",
              "xpReason": "Достижение переломного момента.",
              "progressPercentInChapter": 5,
              "progressWeight": 2,
              "medusa": {
                "stateOnStart": "glow",
                "stateOnComplete": "delight",
                "commentOnStart": "Какой огромный котёл... И Мелина рядом. Она готова. А ты готов? Давай проверим наши записи, чтобы ничего не забыть.",
                "commentOnComplete": "Мы всё проверили. Пора. Пусть пламя очистит путь к Эрдтри!",
                "thoughts": "Этот момент — как прыжок в бездну. Страшно, но мы вместе. Впереди — финал."
              },
              "lore": "Кузница Великанов — единственное место, где можно зажечь пламя, способное сжечь колючки Эрдтри. Мелина пожертвует собой, чтобы открыть нам путь, или же мы можем призвать Яростное Пламя.",
              "rewards": ["Благодать «Кузница Великанов»", "Возможность сжечь Древо"],
              "stateEffects": ["Кузница активирована"]
            }
          ]
        }
      ]
    }
  ]
}